ca_apm_agent/__init__.py
ca_apm_agent/agent.py
ca_apm_agent/config.py
ca_apm_agent/global_constants.py
ca_apm_agent/status.py
ca_apm_agent/bootstrap/__init__.py
ca_apm_agent/bootstrap/sitecustomize.py
ca_apm_agent/connections/__init__.py
ca_apm_agent/connections/_connect.py
ca_apm_agent/connections/command.py
ca_apm_agent/connections/constants.py
ca_apm_agent/connections/data.py
ca_apm_agent/correlation/__init__.py
ca_apm_agent/correlation/correlation.py
ca_apm_agent/directives/__init__.py
ca_apm_agent/directives/agent.profile
ca_apm_agent/directives/instrument.pbd
ca_apm_agent/instruments/__init__.py
ca_apm_agent/instruments/import_hook.py
ca_apm_agent/logging_handlers/__init__.py
ca_apm_agent/patchers/__init__.py
ca_apm_agent/patchers/constants.py
ca_apm_agent/patchers/fork_handler.py
ca_apm_agent/patchers/monkey.py
ca_apm_agent/probes/__init__.py
ca_apm_agent/probes/error.py
ca_apm_agent/probes/timing_probe.py
ca_apm_agent/probes/aiohttp/__init__.py
ca_apm_agent/probes/aiohttp/aiohttp.py
ca_apm_agent/probes/aiohttp/aiohttp_server_http_error.py
ca_apm_agent/probes/aiohttp/aiohttpserver.py
ca_apm_agent/probes/aiohttp/http_error_status_code.py
ca_apm_agent/probes/django/__init__.py
ca_apm_agent/probes/django/dbapi.py
ca_apm_agent/probes/django/http.py
ca_apm_agent/probes/django/http_error.py
ca_apm_agent/probes/flask/__init__.py
ca_apm_agent/probes/flask/http.py
ca_apm_agent/probes/flask/http_error.py
ca_apm_agent/probes/mongodb/__init__.py
ca_apm_agent/probes/mongodb/mongodbcontextinfo.py
ca_apm_agent/probes/mongodb/mongodbcreate.py
ca_apm_agent/probes/mongodb/mongodbdelete.py
ca_apm_agent/probes/mongodb/mongodbread.py
ca_apm_agent/probes/mongodb/mongodbupdate.py
ca_apm_agent/probes/rasa/__init__.py
ca_apm_agent/probes/rasa/rasa.py
ca_apm_agent/probes/rasa/rasaaction.py
ca_apm_agent/probes/redis/__init__.py
ca_apm_agent/probes/redis/clients/RedisProbe.py
ca_apm_agent/probes/redis/clients/__init__.py
ca_apm_agent/probes/requests/__init__.py
ca_apm_agent-2.0.7.dist-info/licenses/LICENSE.txt
ca_apm_agent-2.0.7.dist-info/METADATA
ca_apm_agent-2.0.7.dist-info/WHEEL
ca_apm_agent-2.0.7.dist-info/entry_points.txt
ca_apm_agent-2.0.7.dist-info/top_level.txt
ca_apm_agent-2.0.7.dist-info/RECORD
