Metadata-Version: 2.4
Name: ca-apm-agent
Version: 2.0.7
Summary: Python Agent for CA APM
Home-page: http://docops.ca.com/rest/ca/product/latest/topic?hid=HID_Python&space=APMSAAS&language=&format=rendered
Author: CA, Inc.
Author-email: TeamAPMLeo@ca.com
License: See package description
Keywords: ca-apm-agent application-performance-monitoring APM apm CA
Classifier: Development Status :: 5 - Production/Stable
Classifier: Framework :: Django
Classifier: Framework :: Flask
Classifier: Intended Audience :: Developers
Classifier: Intended Audience :: System Administrators
Classifier: Intended Audience :: Information Technology
Classifier: License :: Other/Proprietary License
Classifier: Programming Language :: Python :: 3
Requires-Python: >=3.0
License-File: LICENSE.txt
Provides-Extra: dev
Requires-Dist: check-manifest; extra == "dev"
Provides-Extra: test
Requires-Dist: coverage; extra == "test"
Dynamic: author
Dynamic: author-email
Dynamic: classifier
Dynamic: description
Dynamic: home-page
Dynamic: keywords
Dynamic: license
Dynamic: license-file
Dynamic: provides-extra
Dynamic: requires-python
Dynamic: summary
